{
  "last_update": "2026-04-11T20:50:34.468566+00:00",
  "source": "CryptoCompare",
  "data": [
    {
      "symbol": "BTC",
      "name": "Bitcoin",
      "current_price": 73474.41,
      "price_change_percentage_24h": 0,
      "high_24h": 74943.89820000001,
      "low_24h": 72004.9218
    },
    {
      "symbol": "ETH",
      "name": "Ethereum",
      "current_price": 2302.61,
      "price_change_percentage_24h": 0,
      "high_24h": 2348.6622,
      "low_24h": 2256.5578
    },
    {
      "symbol": "SOL",
      "name": "Solana",
      "current_price": 85.52,
      "price_change_percentage_24h": 0,
      "high_24h": 87.2304,
      "low_24h": 83.80959999999999
    }
  ]
}