{
  "last_update": "2026-05-13T22:38:07.283940+00:00",
  "source": "CryptoCompare",
  "data": [
    {
      "id": "bitcoin",
      "symbol": "BTC",
      "name": "Bitcoin",
      "current_price": 79240.1464589247,
      "price_change_percentage_24h": -1.74,
      "market_cap": 1587097882300.2375,
      "high_24h": 81287.5503419758,
      "low_24h": 78713.9307166675
    },
    {
      "id": "ethereum",
      "symbol": "ETH",
      "name": "Ethereum",
      "current_price": 2252.97018961886,
      "price_change_percentage_24h": -1.29,
      "market_cap": 271902500774.77667,
      "high_24h": 2322.8563726566,
      "low_24h": 2233.39565586966
    },
    {
      "id": "binancecoin",
      "symbol": "BNB",
      "name": "BNB",
      "current_price": 670.0454780289385,
      "price_change_percentage_24h": 0.6,
      "market_cap": 90312424702.24303,
      "high_24h": 685.5169053630143,
      "low_24h": 663.4511039449541
    },
    {
      "id": "solana",
      "symbol": "SOL",
      "name": "Solana",
      "current_price": 91.0263689654188,
      "price_change_percentage_24h": -3.84,
      "market_cap": 57014922724.81734,
      "high_24h": 95.9530141643657,
      "low_24h": 90.2362665365477
    },
    {
      "id": "ripple",
      "symbol": "XRP",
      "name": "XRP",
      "current_price": 1.42335128660189,
      "price_change_percentage_24h": -1.14,
      "market_cap": 142314732101.72617,
      "high_24h": 1.46903729987979,
      "low_24h": 1.41115349048327
    },
    {
      "id": "cardano",
      "symbol": "ADA",
      "name": "Cardano",
      "current_price": 0.263140395606784,
      "price_change_percentage_24h": -3.14,
      "market_cap": 11841317802.305279,
      "high_24h": 0.277513756920634,
      "low_24h": 0.261283561073099
    },
    {
      "id": "dogecoin",
      "symbol": "DOGE",
      "name": "Dogecoin",
      "current_price": 0.112839991737019,
      "price_change_percentage_24h": 2.36,
      "market_cap": 19175854775.004883,
      "high_24h": 0.114632105867488,
      "low_24h": 0.1096391584145
    },
    {
      "id": "polkadot",
      "symbol": "DOT",
      "name": "Polkadot",
      "current_price": 1.3252914596449,
      "price_change_percentage_24h": -0.97,
      "market_cap": 2231343874.613195,
      "high_24h": 1.436764180249,
      "low_24h": 1.31616273150521
    },
    {
      "id": "avalanche-2",
      "symbol": "AVAX",
      "name": "Avalanche",
      "current_price": 9.73121078105781,
      "price_change_percentage_24h": -1.41,
      "market_cap": 4509842650.912556,
      "high_24h": 10.154772634347,
      "low_24h": 9.62080790794362
    },
    {
      "id": "chainlink",
      "symbol": "LINK",
      "name": "Chainlink",
      "current_price": 10.1708636459213,
      "price_change_percentage_24h": -1.37,
      "market_cap": 10170863645.921299,
      "high_24h": 10.7982454980735,
      "low_24h": 10.0363508078207
    },
    {
      "id": "tron",
      "symbol": "TRX",
      "name": "Tron",
      "current_price": 0.3495609935512102,
      "price_change_percentage_24h": 0.05,
      "market_cap": 33137868425.44397,
      "high_24h": 0.351549301878631,
      "low_24h": 0.348316761624867
    },
    {
      "id": "polygon",
      "symbol": "MATIC",
      "name": "Polygon",
      "current_price": 0.1995,
      "price_change_percentage_24h": 0.0,
      "market_cap": 1989403144.1028385,
      "high_24h": 0.1995,
      "low_24h": 0.1995
    },
    {
      "id": "shiba-inu",
      "symbol": "SHIB",
      "name": "Shiba Inu",
      "current_price": 6.26848697079352e-06,
      "price_change_percentage_24h": -2.59,
      "market_cap": 3695940503.444425,
      "high_24h": 6.55784835700075e-06,
      "low_24h": 6.21228562850777e-06
    },
    {
      "id": "litecoin",
      "symbol": "LTC",
      "name": "Litecoin",
      "current_price": 56.7855571898747,
      "price_change_percentage_24h": -1.96,
      "market_cap": 4381917612.933987,
      "high_24h": 58.9326862342422,
      "low_24h": 56.2786146672258
    },
    {
      "id": "uniswap",
      "symbol": "UNI",
      "name": "Uniswap",
      "current_price": 3.62128550076255,
      "price_change_percentage_24h": -4.01,
      "market_cap": 3621285500.76255,
      "high_24h": 3.8434942388249,
      "low_24h": 3.57934701447562
    }
  ]
}