{
  "last_update": "2026-04-15T15:37:08.294228+00:00",
  "source": "CryptoCompare",
  "data": [
    {
      "symbol": "BTC",
      "name": "Bitcoin",
      "current_price": 73689.97,
      "price_change_percentage_24h": 0,
      "high_24h": 75163.7694,
      "low_24h": 72216.1706
    },
    {
      "symbol": "ETH",
      "name": "Ethereum",
      "current_price": 2324.14,
      "price_change_percentage_24h": 0,
      "high_24h": 2370.6228,
      "low_24h": 2277.6571999999996
    },
    {
      "symbol": "SOL",
      "name": "Solana",
      "current_price": 83.75,
      "price_change_percentage_24h": 0,
      "high_24h": 85.425,
      "low_24h": 82.075
    }
  ]
}