{
  "last_update": "2026-04-27T22:12:22.578309+00:00",
  "source": "CryptoCompare",
  "data": [
    {
      "symbol": "BTC",
      "name": "Bitcoin",
      "current_price": 76869.54,
      "price_change_percentage_24h": 0,
      "high_24h": 78406.9308,
      "low_24h": 75332.14919999999
    },
    {
      "symbol": "ETH",
      "name": "Ethereum",
      "current_price": 2288.96,
      "price_change_percentage_24h": 0,
      "high_24h": 2334.7392,
      "low_24h": 2243.1808
    },
    {
      "symbol": "SOL",
      "name": "Solana",
      "current_price": 84.36,
      "price_change_percentage_24h": 0,
      "high_24h": 86.0472,
      "low_24h": 82.6728
    }
  ]
}